scgravity/__init__.py
scgravity-0.1.0.dist-info/licenses/LICENSE
scgravity-0.1.0.dist-info/METADATA
scgravity-0.1.0.dist-info/WHEEL
scgravity-0.1.0.dist-info/top_level.txt
scgravity-0.1.0.dist-info/RECORD
