Metadata-Version: 2.4
Name: scgravity
Version: 0.1.0
Summary: Self-consistent flow decomposition using a gravity model
Home-page: https://github.com/yourusername/scgravity
Author: Daekyung Lee
License: MIT
Classifier: Programming Language :: Python :: 3
Classifier: License :: OSI Approved :: MIT License
Classifier: Operating System :: OS Independent
Requires-Python: >=3.6
License-File: LICENSE
Requires-Dist: numpy
Dynamic: author
Dynamic: classifier
Dynamic: description
Dynamic: description-content-type
Dynamic: home-page
Dynamic: license
Dynamic: license-file
Dynamic: requires-dist
Dynamic: requires-python
Dynamic: summary
